corslib/__init__.py
corslib/policy.py
corslib/utils.py
corslib-0.0.2.dist-info/LICENSE
corslib-0.0.2.dist-info/METADATA
corslib-0.0.2.dist-info/WHEEL
corslib-0.0.2.dist-info/top_level.txt
corslib-0.0.2.dist-info/RECORD
